ow/__init__.py
ow-0.0.6.dist-info/licenses/LICENSE
ow-0.0.6.dist-info/METADATA
ow-0.0.6.dist-info/WHEEL
ow-0.0.6.dist-info/top_level.txt
ow-0.0.6.dist-info/RECORD
