Metadata-Version: 2.4
Name: ow
Version: 0.0.6
Summary: functions that work on soup
Home-page: https://github.com/t-c-w/ow
Author: Thor Whalen
License: apache-2.0
Platform: any
License-File: LICENSE
Dynamic: license-file
